odoo/addons/stock_full_location_reservation_on_assign/README.rst
odoo/addons/stock_full_location_reservation_on_assign/__init__.py
odoo/addons/stock_full_location_reservation_on_assign/__manifest__.py
odoo/addons/stock_full_location_reservation_on_assign/i18n/it.po
odoo/addons/stock_full_location_reservation_on_assign/i18n/stock_full_location_reservation_on_assign.pot
odoo/addons/stock_full_location_reservation_on_assign/models/__init__.py
odoo/addons/stock_full_location_reservation_on_assign/models/stock_picking.py
odoo/addons/stock_full_location_reservation_on_assign/models/stock_picking_type.py
odoo/addons/stock_full_location_reservation_on_assign/readme/CONFIGURE.rst
odoo/addons/stock_full_location_reservation_on_assign/readme/CONTRIBUTORS.rst
odoo/addons/stock_full_location_reservation_on_assign/readme/DESCRIPTION.rst
odoo/addons/stock_full_location_reservation_on_assign/static/description/icon.png
odoo/addons/stock_full_location_reservation_on_assign/static/description/index.html
odoo/addons/stock_full_location_reservation_on_assign/tests/__init__.py
odoo/addons/stock_full_location_reservation_on_assign/tests/test_full_location_reservation_on_assign.py
odoo/addons/stock_full_location_reservation_on_assign/views/stock_picking_type_views.xml
odoo14_addon_stock_full_location_reservation_on_assign-14.0.1.0.1.dev4.dist-info/METADATA
odoo14_addon_stock_full_location_reservation_on_assign-14.0.1.0.1.dev4.dist-info/WHEEL
odoo14_addon_stock_full_location_reservation_on_assign-14.0.1.0.1.dev4.dist-info/top_level.txt
odoo14_addon_stock_full_location_reservation_on_assign-14.0.1.0.1.dev4.dist-info/RECORD
